setup.py
src/Toster.egg-info/PKG-INFO
src/Toster.egg-info/SOURCES.txt
src/Toster.egg-info/dependency_links.txt
src/Toster.egg-info/entry_points.txt
src/Toster.egg-info/requires.txt
src/Toster.egg-info/top_level.txt
src/toster/__init__.py
src/toster/manager.py
src/toster/runner.py
src/toster/testcase.py