Metadata-Version: 1.0
Name: Toster
Version: 0.1.1
Summary: unittest wrapper with ready to configure command line
Home-page: UNKNOWN
Author: UNKNOWN
Author-email: UNKNOWN
License: UNKNOWN
Platform: UNKNOWN
